<?xml version='1.0' encoding='UTF-8'?>
<osm version='0.6' upload='true' generator='se.kodapan.osm.xml.OsmXmlWriter'>
	<node id='-1' lat='59.26737986714448' lon='15.202211349378121' >
		<tag k='isced:level' v='4' />
		<tag k='amenity' v='school' />
		<tag k='name' v='Virginska gymnasiet' />
		<tag k='source' v='api.karta.orebro.se' />
		<tag k='source:url' v='http://karta2.orebro.se/api/v1/information/808' />
		<tag k='url' v='http://www.orebro.se/virginskagymnasiet' />
	</node>
	<node id='-2' lat='59.25956856109426' lon='15.207925717431804' >
		<tag k='isced:level' v='4' />
		<tag k='amenity' v='school' />
		<tag k='name' v='Tullängsgymnasiet' />
		<tag k='source' v='api.karta.orebro.se' />
		<tag k='source:url' v='http://karta2.orebro.se/api/v1/information/809' />
		<tag k='url' v='http://www.orebro.se/tullangsgymnasiet' />
	</node>
	<node id='-3' lat='59.27060836994942' lon='15.167706935158753' >
		<tag k='isced:level' v='4' />
		<tag k='amenity' v='school' />
		<tag k='name' v='Risbergska gymnasiet' />
		<tag k='source' v='api.karta.orebro.se' />
		<tag k='source:url' v='http://karta2.orebro.se/api/v1/information/810' />
		<tag k='url' v='http://www.orebro.se/risbergskagymnasiet' />
	</node>
	<node id='-4' lat='59.27464427510555' lon='15.218115013499254' >
		<tag k='isced:level' v='4' />
		<tag k='amenity' v='school' />
		<tag k='name' v='Karolinska gymnasiet' />
		<tag k='source' v='api.karta.orebro.se' />
		<tag k='source:url' v='http://karta2.orebro.se/api/v1/information/811' />
		<tag k='url' v='http://www.orebro.se/karolinskagymnasiet' />
	</node>
	<node id='-5' lat='59.26869501386865' lon='15.212886302953562' >
		<tag k='isced:level' v='4' />
		<tag k='amenity' v='school' />
		<tag k='name' v='Rudbecksgymnasiet' />
		<tag k='source' v='api.karta.orebro.se' />
		<tag k='source:url' v='http://karta2.orebro.se/api/v1/information/812' />
		<tag k='url' v='http://www.ru.orebro.se/' />
	</node>
	<node id='-6' lat='59.355305263816334' lon='15.239098586979322' >
		<tag k='isced:level' v='4' />
		<tag k='amenity' v='school' />
		<tag k='name' v='Kvinnerstagymnasiet' />
		<tag k='source' v='api.karta.orebro.se' />
		<tag k='source:url' v='http://karta2.orebro.se/api/v1/information/813' />
		<tag k='url' v='http://www.orebro.se/kvinnerstagymnasiet' />
	</node>
	<node id='-7' lat='59.26627786072714' lon='15.2007753522465' >
		<tag k='isced:level' v='4' />
		<tag k='amenity' v='school' />
		<tag k='name' v='Riksgymnasiet för döva RGD och Riksgymnasiet för hörselskadade, RGH' />
		<tag k='source' v='api.karta.orebro.se' />
		<tag k='source:url' v='http://karta2.orebro.se/api/v1/information/815' />
		<tag k='url' v='http://www.orebro.se/riksgymnasier.rgd-rgh' />
	</node>
	<node id='-8' lat='59.258365718881294' lon='15.204089631887097' >
		<tag k='isced:level' v='4' />
		<tag k='amenity' v='school' />
		<tag k='name' v='Rockgymnasiet' />
		<tag k='source' v='api.karta.orebro.se' />
		<tag k='source:url' v='http://karta2.orebro.se/api/v1/information/816' />
		<tag k='url' v='http://www.rockgymnasiet.se/' />
	</node>
	<node id='-9' lat='59.27770744615223' lon='15.193256414400667' >
		<tag k='isced:level' v='4' />
		<tag k='amenity' v='school' />
		<tag k='name' v='IT-gymnasiet' />
		<tag k='source' v='api.karta.orebro.se' />
		<tag k='source:url' v='http://karta2.orebro.se/api/v1/information/817' />
		<tag k='url' v='http://www.it-gymnasiet.se/' />
	</node>
	<node id='-10' lat='59.276009618567365' lon='15.206496147046108' >
		<tag k='isced:level' v='4' />
		<tag k='amenity' v='school' />
		<tag k='name' v='Jensen gymnasium' />
		<tag k='source' v='api.karta.orebro.se' />
		<tag k='source:url' v='http://karta2.orebro.se/api/v1/information/820' />
		<tag k='url' v='http://www.jenseneducation.se/Gymnasium/' />
	</node>
	<node id='-11' lat='59.272821019335254' lon='15.212042520369499' >
		<tag k='isced:level' v='4' />
		<tag k='amenity' v='school' />
		<tag k='name' v='Thorén Business School' />
		<tag k='source' v='api.karta.orebro.se' />
		<tag k='source:url' v='http://karta2.orebro.se/api/v1/information/821' />
		<tag k='url' v='http://www.gymnasium.se/Thoren_Business_School_Oerebro__b3736.html' />
	</node>
	<node id='-12' lat='59.26077575326425' lon='15.189633885269183' >
		<tag k='isced:level' v='4' />
		<tag k='amenity' v='school' />
		<tag k='name' v='Örebro praktiska gymnasium' />
		<tag k='source' v='api.karta.orebro.se' />
		<tag k='source:url' v='http://karta2.orebro.se/api/v1/information/822' />
		<tag k='url' v='http://www.praktiska.se/' />
	</node>
	<node id='-13' lat='59.26439298365208' lon='15.24273745156317' >
		<tag k='isced:level' v='4' />
		<tag k='amenity' v='school' />
		<tag k='name' v='Fordonsutbildningar' />
		<tag k='source' v='api.karta.orebro.se' />
		<tag k='source:url' v='http://karta2.orebro.se/api/v1/information/823' />
		<tag k='url' v='http://www.fordonsutbildningar.com/' />
	</node>
	<node id='-14' lat='59.27642225395704' lon='15.208365881768373' >
		<tag k='isced:level' v='4' />
		<tag k='amenity' v='school' />
		<tag k='name' v='Plusgymnasiet' />
		<tag k='source' v='api.karta.orebro.se' />
		<tag k='source:url' v='http://karta2.orebro.se/api/v1/information/824' />
		<tag k='url' v='http://plusgymnasiet.se/' />
	</node>
	<node id='-15' lat='59.2778563984533' lon='15.193429158066454' >
		<tag k='isced:level' v='4' />
		<tag k='amenity' v='school' />
		<tag k='name' v='Rytmus musikergymnasiet' />
		<tag k='source' v='api.karta.orebro.se' />
		<tag k='source:url' v='http://karta2.orebro.se/api/v1/information/880' />
		<tag k='url' v='http://www.rytmus.se/%C3%96rebro/V%C3%A5rskola.aspx' />
	</node>
	<node id='-16' lat='59.27757093226407' lon='15.191916851256957' >
		<tag k='isced:level' v='4' />
		<tag k='amenity' v='school' />
		<tag k='name' v='Liaskolan, gymnasiesärskola' />
		<tag k='source' v='api.karta.orebro.se' />
		<tag k='source:url' v='http://karta2.orebro.se/api/v1/information/881' />
		<tag k='url' v='http://liaskolan.se/' />
	</node>
	<node id='-17' lat='59.26853131556072' lon='15.179961277992328' >
		<tag k='isced:level' v='4' />
		<tag k='amenity' v='school' />
		<tag k='name' v='Yrkesgymnasiet' />
		<tag k='source' v='api.karta.orebro.se' />
		<tag k='source:url' v='http://karta2.orebro.se/api/v1/information/882' />
		<tag k='url' v='http://yrkesgymnasiet.se/orter/orebro' />
	</node>
</osm>
